[{"rid":"0","rcmd_id":"-JuN0lNnUHK9JrBi5B-V","cat_id":"-JuqqWKp98rZRo_x8SXg","dish_name":"a","date":"1","content":"1234"},
{"rid":"0","rcmd_id":"-JuN0lNnUHK9JrBi5B-V","cat_id":"-JuqqWKp98rZRo_x8SXg","dish_name":"b","date":"2","content":"1234"},
{"rid":"0","rcmd_id":"-JuN0lNnUHK9JrBi5B-V","cat_id":"-JuqqWKp98rZRo_x8SXg","dish_name":"c","date":"3","content":"1234"},
{"rid":"0","rcmd_id":"-JuN0lNnUHK9JrBi5B-V","cat_id":"-JuqqWKp98rZRo_x8SXg","dish_name":"d","date":"1","content":"1234"},
{"rid":"0","rcmd_id":"-JuN0lNnUHK9JrBi5B-V","cat_id":"-JuqqWKp98rZRo_x8SXg","dish_name":"e","date":"2","content":"1234"},
{"rid":"0","rcmd_id":"-JuN0lNnUHK9JrBi5B-V","cat_id":"-JuqqWKp98rZRo_x8SXg","dish_name":"f","date":"3","content":"1234"}
]